LICENSE
MANIFEST.in
Makefile
README.md
changelog
setup.py
CSSOnDiet/__init__.py
CSSOnDiet/cod.py
CSSOnDiet.egg-info/PKG-INFO
CSSOnDiet.egg-info/SOURCES.txt
CSSOnDiet.egg-info/dependency_links.txt
CSSOnDiet.egg-info/entry_points.txt
CSSOnDiet.egg-info/top_level.txt
tests/.gitignore
tests/.regression.swp
tests/SYNTAX-tester.cod
tests/arythmetics1.cod
tests/arythmetics1.css
tests/arythmetics1.result.css
tests/comments1.cod
tests/comments1.css
tests/comments1.result.css
tests/defines1.cod
tests/defines1.css
tests/defines1.result.css
tests/defines2mixin.cod
tests/defines2mixin.css
tests/defines2mixin.result.css
tests/ffdos.cod
tests/ffdos.css
tests/ffdos.result.css
tests/ffmac.cod
tests/ffmac.css
tests/ffmac.result.css
tests/ffmix.cod
tests/ffmix.css
tests/ffmix.result.css
tests/ffunix.cod
tests/ffunix.css
tests/ffunix.result.css
tests/flex.cod
tests/flex.css
tests/flex.result.css
tests/header1.cod
tests/header1.css
tests/header1.result.css
tests/include1.cod
tests/include1.css
tests/include1.result.css
tests/include1Z.cod
tests/include1Za.css
tests/include1a.cod
tests/include1b.cod
tests/include1c.cod
tests/include1dir.cod
tests/media1.cod
tests/media1.css
tests/media1.result.css
tests/media2.cod
tests/media2.css
tests/media2.result.css
tests/minify1.cod
tests/minify1.css
tests/minify1.result.css
tests/multipledefines.cod
tests/multipledefines.css
tests/multipledefines.result.css
tests/multipledefinesA.cod
tests/newlines.cod
tests/newlines.css
tests/newlines.result.css
tests/prefixes.cod
tests/prefixes.css
tests/prefixes.result.css
tests/regression
tests/rgba1.cod
tests/rgba1.css
tests/rgba1.result.css
tests/shunit2
tests/stdin.css
tests/stdin.result.css
tests/strings1.cod
tests/strings1.css
tests/strings1.result.css
tests/switches.cod
tests/switches.css
tests/switches.result.css
tests/user-buttons.cod
tests/user-buttons.css
tests/user-buttons.result.css
tests/values.cod
tests/values.css
tests/values.result.css