Metadata-Version: 1.1
Name: CSSOnDiet
Version: 1.8.3
Summary: A preprocessor for designers
Home-page: http://cssondiet.com
Author: Tomasz Wyderka
Author-email: wyderkat@cofoh.com
License: GPL3
Keywords: CSS preprocessor
Platform: UNKNOWN
Classifier: Development Status :: 3 - Alpha
Classifier: Environment :: Console
Classifier: Intended Audience :: Developers
Classifier: License :: OSI Approved :: GNU General Public License v3 (GPLv3)
Classifier: Topic :: Software Development :: Pre-processors
Classifier: Programming Language :: Python :: 2
Classifier: Programming Language :: Python :: 2.6
Classifier: Programming Language :: Python :: 2.7
Classifier: Programming Language :: Python :: 3
Classifier: Programming Language :: Python :: 3.2
Classifier: Programming Language :: Python :: 3.3
Classifier: Programming Language :: Python :: 3.4
